pytest_testslide.py
pytest_testslide-2.6.3.dist-info/METADATA
pytest_testslide-2.6.3.dist-info/WHEEL
pytest_testslide-2.6.3.dist-info/top_level.txt
pytest_testslide-2.6.3.dist-info/RECORD
