Metadata-Version: 2.1
Name: pytest-testslide
Version: 2.6.3
Summary: TestSlide fixture for pytest
Home-page: https://github.com/facebookincubator/TestSlide/tree/master/pytest-testslide
Maintainer: Balint Csergo
Maintainer-email: deathowlzz@gmail.com
License: MIT
Platform: UNKNOWN
Classifier: Development Status :: 5 - Production/Stable
Classifier: Intended Audience :: Developers
Classifier: License :: OSI Approved :: MIT License
Classifier: Operating System :: POSIX :: Linux
Classifier: Programming Language :: Python :: 3
Classifier: Topic :: Software Development :: Testing
Classifier: Topic :: Software Development :: Testing :: Acceptance
Classifier: Topic :: Software Development :: Testing :: BDD
Classifier: Topic :: Software Development :: Testing :: Mocking
Classifier: Topic :: Software Development :: Testing :: Unit  
Requires-Dist: testslide (>=2.6.3)
Requires-Dist: pytest (~=6.2)
Requires-Dist: pytest-asyncio (>=0.14.0)
Provides-Extra: build
Requires-Dist: black ; extra == 'build'
Requires-Dist: flake8 ; extra == 'build'
Requires-Dist: mypy ; extra == 'build'
